sympy_addons/__init__.py
sympy_addons/calculus.py
sympy_addons/graphviz.py
sympy_addons/query.py
sympy_addons/rewrite.py
sympy_addons/styling.py
sympy_addons/tests/__init__.py
sympy_addons/tests/test_calculus.py
sympy_addons/tests/test_query.py
sympy_addons/tests/test_rewrite.py
sympy_addons/tests/test_styling.py
sympy_addons-0.0.5.dist-info/LICENSE
sympy_addons-0.0.5.dist-info/METADATA
sympy_addons-0.0.5.dist-info/WHEEL
sympy_addons-0.0.5.dist-info/top_level.txt
sympy_addons-0.0.5.dist-info/RECORD
